heros_time_sync/__init__.py
heros_time_sync/main.py
heros_time_sync/main_controller.py
heros_time_sync/main_ui.py
heros_time_syncronizer-0.1.0.dist-info/METADATA
heros_time_syncronizer-0.1.0.dist-info/WHEEL
heros_time_syncronizer-0.1.0.dist-info/entry_points.txt
heros_time_syncronizer-0.1.0.dist-info/top_level.txt
heros_time_syncronizer-0.1.0.dist-info/RECORD
