Metadata-Version: 2.1
Name: heros-time-syncronizer
Version: 0.1.0
Summary: A Time Syncronizer for HEROS
Home-page: http://192.168.0.203:7990/projects/HERO/repos/time_sync/browse
Author: Lee Suhyun
Author-email: shlee2@withtech.co.kr
Classifier: Programming Language :: Python :: 3
Classifier: License :: OSI Approved :: MIT License
Classifier: Operating System :: OS Independent
Requires-Python: >=3.9
Requires-Dist: pyqt5
